{
  "id": "202670N",
  "draw": "26/070",
  "date": "2026-06-30",
  "weekday": "Tue",
  "numbers": [
    12,
    14,
    17,
    18,
    22,
    40
  ],
  "special": 13,
  "snowball": null,
  "totalInvestment": "72532134",
  "jackpot": "30824589",
  "unitBet": 10,
  "firstPrizeDividend": "39000000",
  "prizes": [
    {
      "tier": 1,
      "winningUnit": 10,
      "dividend": "38908850"
    },
    {
      "tier": 2,
      "winningUnit": 35,
      "dividend": "769930"
    },
    {
      "tier": 3,
      "winningUnit": 1065,
      "dividend": "67470"
    },
    {
      "tier": 4,
      "winningUnit": 3595,
      "dividend": "9600"
    },
    {
      "tier": 5,
      "winningUnit": 58386,
      "dividend": "640"
    },
    {
      "tier": 6,
      "winningUnit": 86251,
      "dividend": "320"
    },
    {
      "tier": 7,
      "winningUnit": 1124307,
      "dividend": "40"
    }
  ],
  "nextDraw": null
}
